konst/__init__.py
konst/json.py
konst/extras/__init__.py
konst/extras/drf/__init__.py
konst/extras/drf/fields.py
konst/forms/__init__.py
konst/forms/fields.py
konst/models/__init__.py
konst/models/fields.py
konst/tests/__init__.py
konst/tests/models.py
konst/tests/settings.py
konst/tests/tests.py
konst/tests/urls.py
django_konst-3.0.0.dist-info/LICENSE
django_konst-3.0.0.dist-info/METADATA
django_konst-3.0.0.dist-info/WHEEL
django_konst-3.0.0.dist-info/top_level.txt
django_konst-3.0.0.dist-info/RECORD
