Metadata-Version: 2.1
Name: django-konst
Version: 3.0.0
Summary: Convenient constants fields for Django
Home-page: https://github.com/lukeburden/django-konst
Author: Luke Burden
Author-email: lukeburden@gmail.com
License: MIT
Classifier: Development Status :: 5 - Production/Stable
Classifier: Environment :: Web Environment
Classifier: Intended Audience :: Developers
Classifier: License :: OSI Approved :: BSD License
Classifier: Operating System :: OS Independent
Classifier: Programming Language :: Python
Classifier: Framework :: Django
License-File: LICENSE
Requires-Dist: django>=3.2
